ldraw/__init__.py
ldraw/__main__.py
ldraw/cli.py
ldraw/colour.py
ldraw/config.py
ldraw/dirs.py
ldraw/download_updates.py
ldraw/downloads.py
ldraw/errors.py
ldraw/figure.py
ldraw/generate.py
ldraw/generation/__init__.py
ldraw/generation/colours.py
ldraw/generation/exceptions.py
ldraw/generation/parts.py
ldraw/geometry.py
ldraw/imports.py
ldraw/ldraw-license.txt
ldraw/lines.py
ldraw/part.py
ldraw/parts.py
ldraw/pieces.py
ldraw/resources.py
ldraw/schemas.py
ldraw/templates/colours.mustache
ldraw/templates/fullparts.mustache
ldraw/templates/ldraw__init__
ldraw/templates/parts.mustache
ldraw/templates/parts__init__.mustache
ldraw/utils.py
pyldraw3-0.11.0.dist-info/WHEEL
pyldraw3-0.11.0.dist-info/entry_points.txt
pyldraw3-0.11.0.dist-info/METADATA
pyldraw3-0.11.0.dist-info/RECORD
