Metadata-Version: 2.4
Name: pyldraw3
Version: 0.11.0
Summary: Python wrapper for LDraw library.
Author: David Boddie, Matthieu Berthomé, Harold Martin
Author-email: David Boddie <david@boddie.org.uk>, Matthieu Berthomé <rienafairefr@gmail.com>, Harold Martin <harold.martin@gmail.com>
License-Expression: GPL-3.0-or-later
Classifier: Development Status :: 4 - Beta
Classifier: Intended Audience :: Developers
Classifier: Programming Language :: Python :: 3.12
Classifier: Programming Language :: Python :: 3.13
Classifier: Topic :: Software Development :: Libraries
Requires-Dist: platformdirs>=4.3.8
Requires-Dist: pystache>=0.6.0
Requires-Dist: progress>=1.6.1
Requires-Dist: requests>=2.32.4
Requires-Dist: inflect>=7.5.0
Requires-Dist: attridict>=0.0.9
Requires-Dist: pyyaml>=6.0.1
Requires-Python: >=3.12
Project-URL: Changelog, https://github.com/hbmartin/pyldraw3/releases
Project-URL: Documentation, https://github.com/hbmartin/pyldraw3/blob/main/GUIDE.md
Project-URL: Homepage, https://github.com/hbmartin/pyldraw3
Project-URL: Repository, https://github.com/hbmartin/pyldraw3
